BroadlinkWifiThermostat/__init__.py
BroadlinkWifiThermostat-2.4.1.dist-info/LICENSE.txt
BroadlinkWifiThermostat-2.4.1.dist-info/METADATA
BroadlinkWifiThermostat-2.4.1.dist-info/WHEEL
BroadlinkWifiThermostat-2.4.1.dist-info/top_level.txt
BroadlinkWifiThermostat-2.4.1.dist-info/RECORD
